elemental_engine/.DS_Store
elemental_engine/__init__.py
elemental_engine/common.py
elemental_engine/__pycache__/__init__.cpython-39.pyc
elemental_engine/__pycache__/common.cpython-39.pyc
elemental_engine/collections/.DS_Store
elemental_engine/collections/__init__.py
elemental_engine/collections/__pycache__/__init__.cpython-39.pyc
elemental_engine/collections/customer/.DS_Store
elemental_engine/collections/customer/__init__.py
elemental_engine/collections/customer/__pycache__/__init__.cpython-39.pyc
elemental_engine/collections/customer/access/__init__.py
elemental_engine/collections/customer/access/indexes.py
elemental_engine/collections/customer/access/__pycache__/__init__.cpython-39.pyc
elemental_engine/collections/customer/access/__pycache__/indexes.cpython-39.pyc
elemental_engine/collections/customer/device/__init__.py
elemental_engine/collections/customer/device/indexes.py
elemental_engine/collections/customer/device/__pycache__/__init__.cpython-39.pyc
elemental_engine/collections/customer/device/__pycache__/indexes.cpython-39.pyc
elemental_engine/collections/customer/store/__init__.py
elemental_engine/collections/customer/store/indexes.py
elemental_engine/collections/customer/store/__pycache__/__init__.cpython-39.pyc
elemental_engine/collections/customer/store/__pycache__/indexes.cpython-39.pyc
elemental_engine/collections/customer/user/__init__.py
elemental_engine/collections/customer/user/indexes.py
elemental_engine/collections/customer/user/__pycache__/__init__.cpython-39.pyc
elemental_engine/collections/customer/user/__pycache__/indexes.cpython-39.pyc
elemental_engine/collections/email/.DS_Store
elemental_engine/collections/email/__init__.py
elemental_engine/collections/email/__pycache__/__init__.cpython-39.pyc
elemental_engine/collections/email/email_schedule/__init__.py
elemental_engine/collections/email/email_schedule/indexes.py
elemental_engine/collections/email/email_schedule/__pycache__/__init__.cpython-39.pyc
elemental_engine-0.0.3.9.6.dist-info/LICENSE
elemental_engine-0.0.3.9.6.dist-info/METADATA
elemental_engine-0.0.3.9.6.dist-info/WHEEL
elemental_engine-0.0.3.9.6.dist-info/top_level.txt
elemental_engine-0.0.3.9.6.dist-info/RECORD
