Metadata-Version: 2.1
Name: elemental-engine
Version: 0.0.3.9.6
Home-page: https://github.com/tomneto/ElementalEngine.git
Author: Elemental (Tom Neto)
Author-email: Tom Neto <info@tomneto.com>
Keywords: python,api
Classifier: Development Status :: 1 - Planning
Classifier: Intended Audience :: Developers
Classifier: Programming Language :: Python :: 3.8
Classifier: Operating System :: Unix
Classifier: Operating System :: MacOS :: MacOS X
Classifier: Operating System :: Microsoft :: Windows
Requires-Python: >=3.8
License-File: LICENSE
Requires-Dist: pymongo
Requires-Dist: certifi
Requires-Dist: python-dotenv
Requires-Dist: uvicorn
Requires-Dist: fastapi
Requires-Dist: chardet
Requires-Dist: psutil
